.gitignore
.pylintrc
.readthedocs.yml
CODE_OF_CONDUCT.md
LICENSE
README.rst
adafruit_icm20649.py
requirements.txt
setup.py
.github/workflows/build.yml
.github/workflows/release.yml
adafruit_circuitpython_icm20649.egg-info/PKG-INFO
adafruit_circuitpython_icm20649.egg-info/SOURCES.txt
adafruit_circuitpython_icm20649.egg-info/dependency_links.txt
adafruit_circuitpython_icm20649.egg-info/requires.txt
adafruit_circuitpython_icm20649.egg-info/top_level.txt
docs/api.rst
docs/conf.py
docs/examples.rst
docs/index.rst
docs/_static/favicon.ico
examples/icm20649_full_test.py
examples/icm20649_simpletest.py