Metadata-Version: 2.1
Name: adafruit-circuitpython-icm20649
Version: 1.0.2
Summary: Library for the ST ICM-20649 Wide-Range 6-DoF Accelerometer and Gyro
Home-page: https://github.com/adafruit/Adafruit_CircuitPython_ICM20649
Author: Adafruit Industries
Author-email: circuitpython@adafruit.com
License: MIT
Keywords: adafruit blinka circuitpython micropython icm20649 gyro accelerometer high-G 6-axis wide range
Platform: UNKNOWN
Classifier: Development Status :: 3 - Alpha
Classifier: Intended Audience :: Developers
Classifier: Topic :: Software Development :: Libraries
Classifier: Topic :: System :: Hardware
Classifier: License :: OSI Approved :: MIT License
Classifier: Programming Language :: Python :: 3
Classifier: Programming Language :: Python :: 3.4
Classifier: Programming Language :: Python :: 3.5
